carbon_verifier/__init__.py
carbon_verifier/main.py
carbon_verifier-0.1.2.dist-info/METADATA
carbon_verifier-0.1.2.dist-info/WHEEL
carbon_verifier-0.1.2.dist-info/top_level.txt
carbon_verifier-0.1.2.dist-info/RECORD
