Metadata-Version: 2.1
Name: carbon_verifier
Version: 0.1.2
Summary: A library to verify Carbon webhook events
Home-page: https://github.com/Carbon-for-Developers/webhook-library.git
Author: carbon
Author-email: team@carbon.ai
Classifier: Programming Language :: Python :: 3
Classifier: License :: OSI Approved :: MIT License
Classifier: Operating System :: OS Independent
Requires-Python: >=3.6
Requires-Dist: requests
